sms77api/Sms77api.py
sms77api/__init__.py
sms77api/classes/Contacts.py
sms77api/classes/Endpoint.py
sms77api/classes/ExtendedEnum.py
sms77api/classes/Hooks.py
sms77api/classes/Journal.py
sms77api/classes/Lookup.py
sms77api/classes/Method.py
sms77api/classes/Pricing.py
sms77api/classes/Status.py
sms77api/classes/__init__.py
sms77api-1.1.0.dist-info/LICENSE
sms77api-1.1.0.dist-info/METADATA
sms77api-1.1.0.dist-info/WHEEL
sms77api-1.1.0.dist-info/top_level.txt
sms77api-1.1.0.dist-info/RECORD
