Metadata-Version: 2.1
Name: sms77api
Version: 1.1.0
Summary: A Python wrapper for the Sms77.io SMS gateway.
Home-page: https://github.com/sms77io/python-client
Author: sms77 e.K.
Author-email: support@sms77.io
License: UNKNOWN
Keywords: sms,text2voice
Platform: UNKNOWN
Classifier: Development Status :: 3 - Alpha
Classifier: Intended Audience :: Developers
Classifier: Topic :: Software Development :: Build Tools
Classifier: License :: OSI Approved :: MIT License
Classifier: Programming Language :: Python :: 3
Classifier: Programming Language :: Python :: 3.5
Classifier: Programming Language :: Python :: 3.6
Classifier: Programming Language :: Python :: 3.7
Classifier: Programming Language :: Python :: 3.8
Classifier: Programming Language :: Python :: 3 :: Only
Requires-Python: >=3.5, <4
Requires-Dist: requests
